plot/__init__.py
plot/stackView.py
utils/__init__.py
utils/binIO.py
waa/__init__.py
waa/ampAttenu.py
waa/bandpass.py
waa/waasub.py
HPGCseismic-0.0.9.dist-info/LICENSE
HPGCseismic-0.0.9.dist-info/METADATA
HPGCseismic-0.0.9.dist-info/WHEEL
HPGCseismic-0.0.9.dist-info/top_level.txt
HPGCseismic-0.0.9.dist-info/RECORD
